README.rst
setup.py
./django_password_validation/__init__.py
./django_password_validation/apps.py
./django_password_validation/common-passwords.txt.gz
./django_password_validation/validators.py
./django_password_validation/locale/en_IE/LC_MESSAGES/django.mo
./django_password_validation/locale/en_IE/LC_MESSAGES/django.po
./django_password_validation/locale/es_ES/LC_MESSAGES/django.mo
./django_password_validation/locale/es_ES/LC_MESSAGES/django.po
./django_password_validation/locale/fr_FR/LC_MESSAGES/django.mo
./django_password_validation/locale/fr_FR/LC_MESSAGES/django.po
./django_password_validation/locale/ga_IE/LC_MESSAGES/django.mo
./django_password_validation/locale/ga_IE/LC_MESSAGES/django.po
./django_password_validation/locale/pt_PT/LC_MESSAGES/django.mo
./django_password_validation/locale/pt_PT/LC_MESSAGES/django.po
django_password_validation_backport.egg-info/PKG-INFO
django_password_validation_backport.egg-info/SOURCES.txt
django_password_validation_backport.egg-info/dependency_links.txt
django_password_validation_backport.egg-info/top_level.txt